{
  "hash": "b2d5030155ff5d699ef5c65f28f6816f",
  "result": {
    "engine": "knitr",
    "markdown": "---\ntitle: \"GMRI Grants Summary - May 20, 2025\"\nformat:\n  html:\n    toc: true\n    toc-depth: 2\n    df-print: paged\n    theme: flatly\n    code-fold: true\n---\n\n\n\n\n\n::: {.cell}\n\n```{.r .cell-code}\ngrants_out\n```\n\n::: {.cell-output-display}\n\n```{=html}\n<div class=\"datatables html-widget html-fill-item\" id=\"htmlwidget-dd12a2862d94980c42ff\" style=\"width:100%;height:auto;\"></div>\n<script type=\"application/json\" data-for=\"htmlwidget-dd12a2862d94980c42ff\">{\"x\":{\"filter\":\"top\",\"vertical\":false,\"filterHTML\":\"<tr>\\n  <td><\\/td>\\n  <td data-type=\\\"character\\\" style=\\\"vertical-align: top;\\\">\\n    <div class=\\\"form-group has-feedback\\\" style=\\\"margin-bottom: auto;\\\">\\n      <input type=\\\"search\\\" placeholder=\\\"All\\\" class=\\\"form-control\\\" style=\\\"width: 100%;\\\"/>\\n      <span class=\\\"glyphicon glyphicon-remove-circle form-control-feedback\\\"><\\/span>\\n    <\\/div>\\n  <\\/td>\\n  <td data-type=\\\"character\\\" style=\\\"vertical-align: top;\\\">\\n    <div class=\\\"form-group has-feedback\\\" style=\\\"margin-bottom: auto;\\\">\\n      <input type=\\\"search\\\" placeholder=\\\"All\\\" class=\\\"form-control\\\" style=\\\"width: 100%;\\\"/>\\n      <span class=\\\"glyphicon glyphicon-remove-circle form-control-feedback\\\"><\\/span>\\n    <\\/div>\\n  <\\/td>\\n  <td data-type=\\\"character\\\" style=\\\"vertical-align: top;\\\">\\n    <div class=\\\"form-group has-feedback\\\" style=\\\"margin-bottom: auto;\\\">\\n      <input type=\\\"search\\\" placeholder=\\\"All\\\" class=\\\"form-control\\\" style=\\\"width: 100%;\\\"/>\\n      <span class=\\\"glyphicon glyphicon-remove-circle form-control-feedback\\\"><\\/span>\\n    <\\/div>\\n  <\\/td>\\n  <td data-type=\\\"time\\\" style=\\\"vertical-align: top;\\\">\\n    <div class=\\\"form-group has-feedback\\\" style=\\\"margin-bottom: auto;\\\">\\n      <input type=\\\"search\\\" placeholder=\\\"All\\\" class=\\\"form-control\\\" style=\\\"width: 100%;\\\"/>\\n      <span class=\\\"glyphicon glyphicon-remove-circle form-control-feedback\\\"><\\/span>\\n    <\\/div>\\n    <div style=\\\"display: none;position: absolute;width: 200px;opacity: 1\\\">\\n      <div data-min=\\\"1745193600000\\\" data-max=\\\"1880150400000\\\"><\\/div>\\n      <span style=\\\"float: left;\\\"><\\/span>\\n      <span style=\\\"float: right;\\\"><\\/span>\\n    <\\/div>\\n  <\\/td>\\n  <td data-type=\\\"time\\\" style=\\\"vertical-align: top;\\\">\\n    <div class=\\\"form-group has-feedback\\\" style=\\\"margin-bottom: auto;\\\">\\n      <input type=\\\"search\\\" placeholder=\\\"All\\\" class=\\\"form-control\\\" style=\\\"width: 100%;\\\"/>\\n      <span class=\\\"glyphicon glyphicon-remove-circle form-control-feedback\\\"><\\/span>\\n    <\\/div>\\n    <div style=\\\"display: none;position: absolute;width: 200px;opacity: 1\\\">\\n      <div data-min=\\\"1236211200000\\\" data-max=\\\"1747699200000\\\"><\\/div>\\n      <span style=\\\"float: left;\\\"><\\/span>\\n      <span style=\\\"float: right;\\\"><\\/span>\\n    <\\/div>\\n  <\\/td>\\n<\\/tr>\",\"data\":[[\"1\",\"2\",\"3\",\"4\",\"5\",\"6\",\"7\",\"8\",\"9\",\"10\",\"11\",\"12\",\"13\",\"14\",\"15\",\"16\",\"17\",\"18\",\"19\",\"20\",\"21\",\"22\",\"23\",\"24\",\"25\",\"26\",\"27\",\"28\",\"29\",\"30\",\"31\",\"32\",\"33\",\"34\",\"35\",\"36\",\"37\",\"38\",\"39\",\"40\",\"41\",\"42\",\"43\",\"44\",\"45\",\"46\",\"47\",\"48\",\"49\",\"50\",\"51\",\"52\",\"53\",\"54\",\"55\",\"56\",\"57\",\"58\",\"59\",\"60\",\"61\",\"62\",\"63\",\"64\",\"65\",\"66\",\"67\",\"68\",\"69\"],[\"MAFMC\",\"Department of Education\",\"NASA Headquarters\",\"U.S. National Science Foundation\",\"Department of Education\",\"Naval Information Warfare Center Pacific\",\"DOC NOAA - ERA Production\",\"69A345 Office of the Under Secretary for Policy\",\"AFRL Kirtland AFB\",\"National Endowment for the Humanities\",\"U.S. National Science Foundation\",\"Department of Education\",\"U.S. National Science Foundation\",\"Foreign Agricultural Service\",\"U.S. National Science Foundation\",\"Department of Education\",\"Agricultural Marketing Service\",\"Department of Education\",\"Department of Education\",\"National Institute of Standards and Technology\",\"Department of Education\",\"Department of Education\",\"U.S. National Science Foundation\",\"U.S. National Science Foundation\",\"Golden Field Office\",\"U.S. National Science Foundation\",\"U.S. National Science Foundation\",\"U.S. National Science Foundation\",\"U.S. National Science Foundation\",\"U.S. National Science Foundation\",\"U.S. National Science Foundation\",\"U.S. National Science Foundation\",\"U.S. National Science Foundation\",\"U.S. National Science Foundation\",\"Office of Naval Research\",\"U.S. National Science Foundation\",\"U.S. National Science Foundation\",\"U.S. National Science Foundation\",\"U.S. National Science Foundation\",\"DARPA - Microsystems Technology Office\",\"U.S. National Science Foundation\",\"U.S. National Science Foundation\",\"U.S. National Science Foundation\",\"U.S. National Science Foundation\",\"U.S. National Science Foundation\",\"U.S. National Science Foundation\",\"National Energy Technology Laboratory\",\"U.S. National Science Foundation\",\"U.S. National Science Foundation\",\"U.S. National Science Foundation\",\"U.S. National Science Foundation\",\"U.S. National Science Foundation\",\"U.S. National Science Foundation\",\"U.S. National Science Foundation\",\"U.S. National Science Foundation\",\"U.S. National Science Foundation\",\"DOC NOAA - ERA Production\",\"U.S. National Science Foundation\",\"DOC NOAA - ERA Production\",\"DOC NOAA - ERA Production\",\"DOC NOAA - ERA Production\",\"NOAA Fisheries\",\"Agency for Health Care Research and Quality\",\"National Park Service\",\"Washington Headquarters Services\",\"Centers for Disease Control and Prevention - ERA\",\"Air Force -- Research Lab\",\"Agency for Health Care Research and Quality\",\"Dept of the Army -- Materiel Command\"],[\"<a href='https://www.mafmc.org/newsfeed/2025/rfp-ecosystem-habitat-indicators' target='_blank'>Mid-Atlantic Council Seeks Contractor to Operationalize Ecosystem and Habitat Indicators to Support Fisheries Management<\\/a>\",\"<a href='https://www.federalregister.gov/documents/2025/04/23/2025-07024/applications-for-new-awards-opportunity-scholarship-program' target='_blank'>Office of Elementary and Secondary Education (OESE): District of Columbia Opportunity Scholarship Program CFDA Number 84.370A<\\/a>\",\"<a href='https://solicitation.nasaprs.com/ROSES2024' target='_blank'>ROSES 2024: E.9 Space Biology: Research Studies<\\/a>\",\"<a href='http://www.nsf.gov/publications/pub_summ.jsp?ods_key=nsf24581' target='_blank'>Cyber-Physical Systems<\\/a>\",\"<a href='https://www.govinfo.gov/content/pkg/FR-2025-05-09/pdf/2025-08092.pdf' target='_blank'>Office of Elementary and Secondary Education (OESE): Expanding Opportunity Through Quality Charter Schools Program (CSP)--Grants to State Entities (State Entity Grants), Assistance Listing Number 84.282A<\\/a>\",\"<a href='NA' target='_blank'>C4ISR, Information Operations, Cyberspace Operations and Information Technology System Research, Cryogenics and Quantum Broad Agency Announcement (BAA)<\\/a>\",\"<a href='NA' target='_blank'>FY 2025 NOAA Coral Reef Conservation Program - Ruth D. Gates: Supporting Hawaii&#8217;s Sustainable Coral Reef Fisheries Management Plans<\\/a>\",\"<a href='NA' target='_blank'>Regional Infrastructure Accelerator Program - NOFO Reissuance<\\/a>\",\"<a href='NA' target='_blank'>Future Scholars for Science, Technology, Engineering, and Mathematics (STEM) Workforce Development Programs<\\/a>\",\"<a href='https://www.neh.gov/grants/preservation/preservation-and-access-education-and-training' target='_blank'>Preservation and Access Education and Training<\\/a>\",\"<a href='http://www.nsf.gov/publications/pub_summ.jsp?ods_key=nsf24587' target='_blank'>Research on the Science and Technology Enterprise: Indicators, Statistics, and Methods (NCSES S&amp;T)<\\/a>\",\"<a href='https://www.govinfo.gov/content/pkg/FR-2025-05-15/pdf/2025-08657.pdf' target='_blank'>Office of Elementary and Secondary Education (OESE): Charter Schools Program (CSP): Grants to Charter Management Organizations for the Replication and Expansion of High-Quality Charter Schools Assistance Listing Number 84.282M<\\/a>\",\"<a href='http://www.nsf.gov/funding/pgm_summ.jsp?pims_id=506410' target='_blank'>Fire Science Innovations through Research and Education<\\/a>\",\"<a href='NA' target='_blank'>UNITED STATES DEPARTMENT OF AGRICULTURE MCGOVERN-DOLE INTERNATIONAL FOOD FOR EDUCATION AND CHILD NUTRITION PROGRAM<\\/a>\",\"<a href='http://www.nsf.gov/publications/pub_summ.jsp?ods_key=nsf24583' target='_blank'>Advanced Computing Systems &amp; Services: Adapting to the Rapid Evolution of Science and Engineering Research 2.0<\\/a>\",\"<a href='https://www.govinfo.gov/content/pkg/FR-2025-05-16/pdf/2025-08783.pdf' target='_blank'>Office of Elementary and Secondary Education (OESE): Charter Schools Program (CSP): Grants for Credit Enhancement for Charter School Facilities (Credit Enhancement), Assistance Listing Number 84.354A<\\/a>\",\"<a href='https://www.ams.usda.gov/services/grants/rfsp' target='_blank'>Regional Food System Partnerships<\\/a>\",\"<a href='https://www.govinfo.gov/content/pkg/FR-2025-05-15/pdf/2025-08660.pdf' target='_blank'>Office of Elementary and Secondary Education (OESE): Charter Schools Program (CSP): CSP Developer Grants for The Opening of New Charter Schools, Assistance Listing Number 84.282B<\\/a>\",\"<a href='https://www.govinfo.gov/content/pkg/FR-2025-05-15/pdf/2025-08660.pdf' target='_blank'>Office of Elementary and Secondary Education (OESE): Charter Schools Program (CSP): CSP Developer Grants for the Replication and Expansion of High-Quality Charter Schools, Assistance Listing Number 84.282E<\\/a>\",\"<a href='NA' target='_blank'>Regional Alliances and Multistakeholder Partnerships to Stimulate (RAMPS) Cybersecurity Education and Workforce Development<\\/a>\",\"<a href='https://www.govinfo.gov/content/pkg/FR-2025-05-09/pdf/2025-08093.pdf' target='_blank'>Office of Elementary and Secondary Education (OESE): Expanding Opportunity Through Quality Charter Schools Program (CSP)&#8212;State Charter School Facilities Incentive Grant (SFIG) Program, Assistance Listing Number (ALN) 84.282D<\\/a>\",\"<a href='https://www.govinfo.gov/content/pkg/FR-2025-05-16/pdf/2025-08766.pdf' target='_blank'>Office of Elementary and Secondary Education (OESE): Charter Schools Program (CSP)- Model Development and Dissemination Grants, Assistance Listing Number (ALN) 84.282G<\\/a>\",\"<a href='http://www.nsf.gov/publications/pub_summ.jsp?ods_key=nsf25523' target='_blank'>EPSCoR Research Infrastructure Improvement Program: EPSCoR Collaborations for Optimizing Research Ecosystems<\\/a>\",\"<a href='http://www.nsf.gov/publications/pub_summ.jsp?ods_key=nsf23510' target='_blank'>Improving Undergraduate STEM Education: Directorate for STEM Education<\\/a>\",\"<a href='https://eere-exchange.energy.gov' target='_blank'>The Circular Supply Chains Accelerator<\\/a>\",\"<a href='http://www.nsf.gov/funding/pgm_summ.jsp?pims_id=505924' target='_blank'>ECosystem for Leading Innovation in Plasma Science and Engineering<\\/a>\",\"<a href='http://www.nsf.gov/publications/pub_summ.jsp?ods_key=nsf24571' target='_blank'>Correctness for Scientific Computing Systems<\\/a>\",\"<a href='http://www.nsf.gov/publications/pub_summ.jsp?ods_key=nsf25522' target='_blank'>EPSCoR Research Infrastructure Improvement Program: EPSCoR Research Incubators for STEM Excellence<\\/a>\",\"<a href='http://www.nsf.gov/publications/pub_summ.jsp?ods_key=nsf23536' target='_blank'>Scholarships in STEM Network<\\/a>\",\"<a href='http://www.nsf.gov/funding/pgm_summ.jsp?pims_id=12729' target='_blank'>Physical Oceanography<\\/a>\",\"<a href='http://www.nsf.gov/funding/pgm_summ.jsp?pims_id=11698' target='_blank'>Chemical Oceanography<\\/a>\",\"<a href='http://www.nsf.gov/funding/pgm_summ.jsp?pims_id=506154' target='_blank'>Biological Oceanography<\\/a>\",\"<a href='http://www.nsf.gov/publications/pub_summ.jsp?ods_key=nsf25539' target='_blank'>Verticals-enabling Intelligent Network Systems<\\/a>\",\"<a href='http://www.nsf.gov/publications/pub_summ.jsp?ods_key=nsf19575' target='_blank'>Methodology, Measurement, and Statistics<\\/a>\",\"<a href='https://www.onr.navy.mil/work-with-us/funding-opportunities/announcements' target='_blank'>FY25 Department of the Navy (DoN) Science, Technology, Engineering, and Mathematics (STEM) Education and Workforce Program<\\/a>\",\"<a href='http://www.nsf.gov/publications/pub_summ.jsp?ods_key=nsf24606' target='_blank'>Pathways to Enable Open-Source Ecosystems<\\/a>\",\"<a href='http://www.nsf.gov/publications/pub_summ.jsp?ods_key=nsf22537' target='_blank'>Geospace Environment Modeling<\\/a>\",\"<a href='http://www.nsf.gov/publications/pub_summ.jsp?ods_key=nsf24584' target='_blank'>Advanced Technological Education<\\/a>\",\"<a href='http://www.nsf.gov/publications/pub_summ.jsp?ods_key=nsf23614' target='_blank'>Smart Health and Biomedical Research in the Era of Artificial Intelligence and Advanced Data Science<\\/a>\",\"<a href='https://sam.gov/opp/49bbf2a87fb44ac6a5ef8c7d5c1ba292/view' target='_blank'>Microsystems Technology Office (MTO) Office-wide<\\/a>\",\"<a href='http://www.nsf.gov/publications/pub_summ.jsp?ods_key=nsf24569' target='_blank'>Mathematical Foundations of Artificial Intelligence<\\/a>\",\"<a href='http://www.nsf.gov/funding/pgm_summ.jsp?pims_id=5690' target='_blank'>Mathematical Biology<\\/a>\",\"<a href='http://www.nsf.gov/publications/pub_summ.jsp?ods_key=nsf22612' target='_blank'>Paleo Perspectives on Present and Projected Climate<\\/a>\",\"<a href='http://www.nsf.gov/publications/pub_summ.jsp?ods_key=nsf25506' target='_blank'>Geosciences Open Science Ecosystem<\\/a>\",\"<a href='http://www.nsf.gov/publications/pub_summ.jsp?ods_key=nsf23584' target='_blank'>IUSE: Innovation in Two-Year College STEM Education<\\/a>\",\"<a href='http://www.nsf.gov/funding/pgm_summ.jsp?pims_id=5556' target='_blank'>Statistics<\\/a>\",\"<a href='https://www.fedconnect.net' target='_blank'>Notice of Intent (NOI) related to &quot;HARMONY: Human-Centric Analytics for Resilient &amp; Modernized Power sYstems&#8221;<\\/a>\",\"<a href='http://www.nsf.gov/publications/pub_summ.jsp?ods_key=nsf23525' target='_blank'>Oceanographic Facilities and Equipment Support<\\/a>\",\"<a href='http://www.nsf.gov/publications/pub_summ.jsp?ods_key=nsf24601' target='_blank'>Advancing Informal STEM Learning<\\/a>\",\"<a href='http://www.nsf.gov/publications/pub_summ.jsp?ods_key=nsf23521' target='_blank'>Strengthening the Cyberinfrastructure Professionals Ecosystem  (SCIPE)<\\/a>\",\"<a href='http://www.nsf.gov/publications/pub_summ.jsp?ods_key=nsf24554' target='_blank'>Artificial Intelligence, Formal Methods, and Mathematical Reasoning<\\/a>\",\"<a href='http://www.nsf.gov/publications/pub_summ.jsp?ods_key=nsf22569' target='_blank'>Algorithms for Modern Power Systems<\\/a>\",\"<a href='http://www.nsf.gov/funding/pgm_summ.jsp?pims_id=12724' target='_blank'>Ocean Technology and Interdisciplinary Coordination<\\/a>\",\"<a href='http://www.nsf.gov/publications/pub_summ.jsp?ods_key=nsf24516' target='_blank'>Partnerships in Astronomy &amp; Astrophysics Research and Education<\\/a>\",\"<a href='http://www.nsf.gov/publications/pub_summ.jsp?ods_key=nsf22548' target='_blank'>EHR Core Research: Building Capacity in STEM Education Research (ECR: BCSER)<\\/a>\",\"<a href='http://www.nsf.gov/publications/pub_summ.jsp?ods_key=nsf25509' target='_blank'>Emerging Mathematics in Biology<\\/a>\",\"<a href='NA' target='_blank'>FY 2024 Atlantic Salmon Habitat Restoration Partnership Grants<\\/a>\",\"<a href='http://www.nsf.gov/publications/pub_summ.jsp?ods_key=nsf24608' target='_blank'>Safety, Security, and Privacy of Open-Source Ecosystems<\\/a>\",\"<a href='NA' target='_blank'>FY 2024 &#8211; 2026 Broad Agency Announcement (BAA), National Marine Fisheries Service<\\/a>\",\"<a href='NA' target='_blank'>FY 2024 &#8211; 2026 - Broad Agency Announcement (BAA) for the Office of Education<\\/a>\",\"<a href='NA' target='_blank'>FY 2024 &#8211; 2026 Broad Agency Announcement (BAA), Office of Oceanic and Atmospheric Research (OAR)<\\/a>\",\"<a href='https://www.fisheries.noaa.gov/grant/fiscal-year-2024-2026-broad-agency-announcement' target='_blank'>Fiscal Year 2024–2026: Broad Agency Announcement<\\/a>\",\"<a href='http://grants.nih.gov/grants/guide/pa-files/PA-24-261.html' target='_blank'>Examining the Impact of Artificial Intelligence (AI) on Healthcare Safety (R18)<\\/a>\",\"<a href='NA' target='_blank'>NPS Cooperative Ecosystems Studies Units (CESU) Master Cooperative Agreements<\\/a>\",\"<a href='NA' target='_blank'>NDEP STEM Open NFO<\\/a>\",\"<a href='https://grants.nih.gov/grants/guide/rfa-files/RFA-OH-25-002.html' target='_blank'>Occupational Safety and Health Education and Research Centers (T42)<\\/a>\",\"<a href='NA' target='_blank'>FOUNDATIONS OF TRUSTED SYSTEMS<\\/a>\",\"<a href='http://grants.nih.gov/grants/guide/pa-files/PA-24-093.html' target='_blank'>Systems-Based Approaches to Improve Patient Safety by Improving Healthcare Worker Safety and Well-Being (R01 Clinical Trial Optional)<\\/a>\",\"<a href='NA' target='_blank'>Department of Defense Research and Education Program for Historically Black Colleges and Universities and Minority-Serving Institutions (HBCU/MI)<\\/a>\"],[\"\",\"\",\"\",\"\",\"\",\"\",\"\",\"\",\"\",\"\",\"\",\"<span style=\\\"color:white; background-color:#28a745; padding:2px 6px; border-radius:4px;\\\">New<\\/span>\",\"\",\"\",\"\",\"<span style=\\\"color:white; background-color:#28a745; padding:2px 6px; border-radius:4px;\\\">New<\\/span>\",\"\",\"<span style=\\\"color:white; background-color:#28a745; padding:2px 6px; border-radius:4px;\\\">New<\\/span>\",\"<span style=\\\"color:white; background-color:#28a745; padding:2px 6px; border-radius:4px;\\\">New<\\/span>\",\"\",\"\",\"<span style=\\\"color:white; background-color:#28a745; padding:2px 6px; border-radius:4px;\\\">New<\\/span>\",\"\",\"\",\"\",\"\",\"\",\"\",\"\",\"\",\"\",\"\",\"<span style=\\\"color:white; background-color:#28a745; padding:2px 6px; border-radius:4px;\\\">New<\\/span>\",\"\",\"\",\"\",\"\",\"\",\"\",\"\",\"\",\"\",\"\",\"\",\"\",\"\",\"\",\"\",\"\",\"\",\"\",\"\",\"\",\"\",\"\",\"\",\"\",\"\",\"\",\"\",\"\",\"\",\"\",\"\",\"\",\"\",\"\",\"\",\"\"],[\"2025-04-21T00:00:00Z\",\"2025-06-02T00:00:00Z\",\"2025-06-02T00:00:00Z\",\"2025-06-02T00:00:00Z\",\"2025-06-09T00:00:00Z\",\"2025-06-09T00:00:00Z\",\"2025-06-13T00:00:00Z\",\"2025-06-16T00:00:00Z\",\"2025-06-17T00:00:00Z\",\"2025-06-17T00:00:00Z\",\"2025-06-17T00:00:00Z\",\"2025-06-18T00:00:00Z\",\"2025-06-20T00:00:00Z\",\"2025-06-23T00:00:00Z\",\"2025-06-24T00:00:00Z\",\"2025-06-25T00:00:00Z\",\"2025-06-27T00:00:00Z\",\"2025-06-30T00:00:00Z\",\"2025-06-30T00:00:00Z\",\"2025-07-01T00:00:00Z\",\"2025-07-08T00:00:00Z\",\"2025-07-14T00:00:00Z\",\"2025-07-15T00:00:00Z\",\"2025-07-16T00:00:00Z\",\"2025-07-18T00:00:00Z\",\"2025-08-12T00:00:00Z\",\"2025-08-12T00:00:00Z\",\"2025-08-12T00:00:00Z\",\"2025-08-14T00:00:00Z\",\"2025-08-15T00:00:00Z\",\"2025-08-15T00:00:00Z\",\"2025-08-15T00:00:00Z\",\"2025-08-25T00:00:00Z\",\"2025-08-28T00:00:00Z\",\"2025-08-29T00:00:00Z\",\"2025-09-02T00:00:00Z\",\"2025-09-30T00:00:00Z\",\"2025-10-02T00:00:00Z\",\"2025-10-03T00:00:00Z\",\"2025-10-09T00:00:00Z\",\"2025-10-10T00:00:00Z\",\"2025-10-14T00:00:00Z\",\"2025-10-20T00:00:00Z\",\"2025-11-14T00:00:00Z\",\"2025-12-10T00:00:00Z\",\"2025-12-15T00:00:00Z\",\"2025-12-31T00:00:00Z\",\"2026-01-12T00:00:00Z\",\"2026-01-14T00:00:00Z\",\"2026-01-15T00:00:00Z\",\"2026-02-05T00:00:00Z\",\"2026-02-09T00:00:00Z\",\"2026-02-16T00:00:00Z\",\"2026-02-17T00:00:00Z\",\"2026-02-27T00:00:00Z\",\"2026-03-02T00:00:00Z\",\"2026-03-31T00:00:00Z\",\"2026-04-28T00:00:00Z\",\"2026-09-30T00:00:00Z\",\"2026-09-30T00:00:00Z\",\"2026-09-30T00:00:00Z\",\"2026-09-30T00:00:00Z\",\"2027-05-25T00:00:00Z\",\"2027-12-31T00:00:00Z\",\"2028-02-08T00:00:00Z\",\"2028-10-26T00:00:00Z\",\"2028-12-05T00:00:00Z\",\"2029-01-19T00:00:00Z\",\"2029-07-31T00:00:00Z\"],[\"2025-04-21T00:00:00Z\",\"2025-04-23T00:00:00Z\",\"2024-12-19T00:00:00Z\",\"2024-06-05T00:00:00Z\",\"2025-05-09T00:00:00Z\",\"2024-06-10T00:00:00Z\",\"2025-04-11T00:00:00Z\",\"2025-05-08T00:00:00Z\",\"2020-06-17T00:00:00Z\",\"2025-04-29T00:00:00Z\",\"2024-07-01T00:00:00Z\",\"2025-05-15T00:00:00Z\",\"2025-03-16T00:00:00Z\",\"2025-05-09T00:00:00Z\",\"2024-06-19T00:00:00Z\",\"2025-05-16T00:00:00Z\",\"2025-05-09T00:00:00Z\",\"2025-05-15T00:00:00Z\",\"2025-05-15T00:00:00Z\",\"2025-05-01T00:00:00Z\",\"2025-05-09T00:00:00Z\",\"2025-05-16T00:00:00Z\",\"2024-12-14T00:00:00Z\",\"2022-10-20T00:00:00Z\",\"2025-01-16T00:00:00Z\",\"2024-01-06T00:00:00Z\",\"2024-05-10T00:00:00Z\",\"2024-12-14T00:00:00Z\",\"2022-12-23T00:00:00Z\",\"2015-03-13T00:00:00Z\",\"2015-03-13T00:00:00Z\",\"2022-12-13T00:00:00Z\",\"2025-05-20T00:00:00Z\",\"2019-04-10T00:00:00Z\",\"2025-01-07T00:00:00Z\",\"2024-09-14T00:00:00Z\",\"2021-12-10T00:00:00Z\",\"2024-06-25T00:00:00Z\",\"2023-08-11T00:00:00Z\",\"2024-05-09T00:00:00Z\",\"2024-05-02T00:00:00Z\",\"2022-07-11T00:00:00Z\",\"2022-07-06T00:00:00Z\",\"2024-11-02T00:00:00Z\",\"2023-05-06T00:00:00Z\",\"2018-03-29T00:00:00Z\",\"2024-09-17T00:00:00Z\",\"2022-12-01T00:00:00Z\",\"2024-08-29T00:00:00Z\",\"2022-11-22T00:00:00Z\",\"2024-03-05T00:00:00Z\",\"2022-02-11T00:00:00Z\",\"2009-03-05T00:00:00Z\",\"2023-12-16T00:00:00Z\",\"2021-12-24T00:00:00Z\",\"2024-11-08T00:00:00Z\",\"2024-02-05T00:00:00Z\",\"2024-09-20T00:00:00Z\",\"2024-07-29T00:00:00Z\",\"2024-08-12T00:00:00Z\",\"2024-10-09T00:00:00Z\",\"2024-07-29T00:00:00Z\",\"2024-07-16T00:00:00Z\",\"2022-12-22T00:00:00Z\",\"2023-02-09T00:00:00Z\",\"2024-10-07T00:00:00Z\",\"2024-12-02T00:00:00Z\",\"2023-12-05T00:00:00Z\",\"2024-08-01T00:00:00Z\"]],\"container\":\"<table class=\\\"display\\\">\\n  <thead>\\n    <tr>\\n      <th> <\\/th>\\n      <th>Agency<\\/th>\\n      <th>Title<\\/th>\\n      <th>Recent<\\/th>\\n      <th>Deadline<\\/th>\\n      <th>Posted<\\/th>\\n    <\\/tr>\\n  <\\/thead>\\n<\\/table>\",\"options\":{\"pageLength\":10,\"autoWidth\":true,\"columnDefs\":[{\"orderable\":false,\"targets\":0},{\"name\":\" \",\"targets\":0},{\"name\":\"Agency\",\"targets\":1},{\"name\":\"Title\",\"targets\":2},{\"name\":\"Recent\",\"targets\":3},{\"name\":\"Deadline\",\"targets\":4},{\"name\":\"Posted\",\"targets\":5}],\"order\":[],\"orderClasses\":false,\"orderCellsTop\":true}},\"evals\":[],\"jsHooks\":[]}</script>\n```\n\n:::\n:::\n",
    "supporting": [],
    "filters": [
      "rmarkdown/pagebreak.lua"
    ],
    "includes": {
      "include-in-header": [
        "<link href=\"site_libs/htmltools-fill-0.5.8.1/fill.css\" rel=\"stylesheet\" />\n<script src=\"site_libs/htmlwidgets-1.6.4/htmlwidgets.js\"></script>\n<link href=\"site_libs/datatables-css-0.0.0/datatables-crosstalk.css\" rel=\"stylesheet\" />\n<script src=\"site_libs/datatables-binding-0.33/datatables.js\"></script>\n<script src=\"site_libs/jquery-3.6.0/jquery-3.6.0.min.js\"></script>\n<link href=\"site_libs/dt-core-1.13.6/css/jquery.dataTables.min.css\" rel=\"stylesheet\" />\n<link href=\"site_libs/dt-core-1.13.6/css/jquery.dataTables.extra.css\" rel=\"stylesheet\" />\n<script src=\"site_libs/dt-core-1.13.6/js/jquery.dataTables.min.js\"></script>\n<link href=\"site_libs/nouislider-7.0.10/jquery.nouislider.min.css\" rel=\"stylesheet\" />\n<script src=\"site_libs/nouislider-7.0.10/jquery.nouislider.min.js\"></script>\n<link href=\"site_libs/selectize-0.12.0/selectize.bootstrap3.css\" rel=\"stylesheet\" />\n<script src=\"site_libs/selectize-0.12.0/selectize.min.js\"></script>\n<link href=\"site_libs/crosstalk-1.2.1/css/crosstalk.min.css\" rel=\"stylesheet\" />\n<script src=\"site_libs/crosstalk-1.2.1/js/crosstalk.min.js\"></script>\n<link href=\"site_libs/pagedtable-1.1/css/pagedtable.css\" rel=\"stylesheet\" />\n<script src=\"site_libs/pagedtable-1.1/js/pagedtable.js\"></script>\n"
      ]
    },
    "engineDependencies": {},
    "preserve": {},
    "postProcess": true
  }
}